helloffyz/__init__.py
helloffyz-1.3.0.dist-info/LICENSE
helloffyz-1.3.0.dist-info/METADATA
helloffyz-1.3.0.dist-info/WHEEL
helloffyz-1.3.0.dist-info/top_level.txt
helloffyz-1.3.0.dist-info/RECORD
