Metadata-Version: 2.1
Name: helloffyz
Version: 1.3.0
Summary: try to upload a pypi package
Home-page: https://github.com/xjgg1221/helloffyz-pypi
Author: ffyz
Author-email: xj99gg@gmail.com
Requires-Python: >=3.6
License-File: LICENSE
